Metadata-Version: 1.0
Name: ruitestpackage2
Version: 0.0.3
Summary: This is test package.
Home-page: UNKNOWN
Author: UNKNOWN
Author-email: UNKNOWN
License: UNKNOWN
Platform: UNKNOWN
